langchain_yugabytedb/__init__.py
langchain_yugabytedb/async_vectorstore.py
langchain_yugabytedb/chat_message_histories.py
langchain_yugabytedb/indexes.py
langchain_yugabytedb/translator.py
langchain_yugabytedb/vectorstores.py
langchain_yugabytedb/yb_engine.py
langchain_yugabytedb-0.0.4.dist-info/METADATA
langchain_yugabytedb-0.0.4.dist-info/WHEEL
langchain_yugabytedb-0.0.4.dist-info/licenses/LICENSE
langchain_yugabytedb-0.0.4.dist-info/RECORD
