Metadata-Version: 2.4
Name: langchain-yugabytedb
Version: 0.0.4
Summary: An integration package connecting YugabyteDB and LangChain
Author-email: Yugabyte <nikhil@yugabyte.com>
License-Expression: MIT
License-File: LICENSE
Requires-Python: >=3.9
Requires-Dist: asyncpg>=0.30.0
Requires-Dist: greenlet>=3.2.3
Requires-Dist: langchain-core<0.4.0,>=0.2.13
Requires-Dist: numpy<3,>=1.21
Requires-Dist: pgvector<0.4,>=0.2.5
Requires-Dist: psycopg-pool<4,>=3.2.1
Requires-Dist: psycopg<4,>=3
Requires-Dist: sqlalchemy<3,>=2
